conducta/__init__.py
conducta/core/__init__.py
conducta/core/credentials.py
conducta/core/logger.py
conducta/providers/__init__.py
conducta/providers/openai.py
conducta-0.0.3.dist-info/LICENSE
conducta-0.0.3.dist-info/METADATA
conducta-0.0.3.dist-info/WHEEL
conducta-0.0.3.dist-info/RECORD
