Metadata-Version: 2.1
Name: conducta
Version: 0.0.3
Summary: A model orchestration library for the modern AI era with a focus on excellent developer experience.
Home-page: https://github.com/drew-worden/conducta
Author: drew-worden
Author-email: drew.p.worden@gmail.com
Requires-Python: >=3.12,<4.0
Classifier: Programming Language :: Python :: 3
Classifier: Programming Language :: Python :: 3.12
Project-URL: Repository, https://github.com/drew-worden/conducta
